console_apps/__init__.py
console_apps/afe_main_os.py
console_apps/afe_main_os_unsupervised.py
organon/__init__.py
organon/afe/__init__.py
organon/afe/core/__init__.py
organon/afe/core/businessobjects/__init__.py
organon/afe/core/businessobjects/afe_static_objects.py
organon/afe/data/__init__.py
organon/afe/data/base_df.zip
organon/afe/data/cash_df.zip
organon/afe/data/score_df.zip
organon/afe/dataaccess/__init__.py
organon/afe/dataaccess/helpers/__init__.py
organon/afe/dataaccess/helpers/record_source_helper.py
organon/afe/dataaccess/services/__init__.py
organon/afe/dataaccess/services/base_record_reader.py
organon/afe/dataaccess/services/i_sample_data_service.py
organon/afe/dataaccess/services/sample_data_service.py
organon/afe/dataaccess/services/sample_data_service_helper.py
organon/afe/dataaccess/services/target_file_record_repository.py
organon/afe/dataaccess/services/transaction_file_record_reader.py
organon/afe/domain/__init__.py
organon/afe/domain/common/__init__.py
organon/afe/domain/common/afe_date_helper.py
organon/afe/domain/common/base_execution_plan_service.py
organon/afe/domain/common/persist_helper.py
organon/afe/domain/common/reader_helper.py
organon/afe/domain/common/runtime_stats_service.py
organon/afe/domain/enums/__init__.py
organon/afe/domain/enums/afe_date_column_encoding_type.py
organon/afe/domain/enums/afe_date_column_type.py
organon/afe/domain/enums/afe_learning_type.py
organon/afe/domain/enums/afe_operator.py
organon/afe/domain/enums/afe_target_column_type.py
organon/afe/domain/enums/binary_target_class.py
organon/afe/domain/enums/date_resolution.py
organon/afe/domain/enums/record_source_type.py
organon/afe/domain/modelling/__init__.py
organon/afe/domain/modelling/abstract_modelling_service.py
organon/afe/domain/modelling/auto_column_type_decider_service.py
organon/afe/domain/modelling/base_modelling_service.py
organon/afe/domain/modelling/businessobjects/__init__.py
organon/afe/domain/modelling/businessobjects/afe_column.py
autonon-0.4.1.dist-info/LICENSE
autonon-0.4.1.dist-info/METADATA
autonon-0.4.1.dist-info/WHEEL
autonon-0.4.1.dist-info/top_level.txt
autonon-0.4.1.dist-info/RECORD
