Metadata-Version: 2.1
Name: autonon
Version: 0.4.1
Summary: Organon Automated ML Platform
Home-page: https://gitlab.com/organon-os/autonon
Author: Organon Analytics
Author-email: support@organonanalytics.com
License: UNKNOWN
Platform: UNKNOWN
Classifier: Programming Language :: Python :: 3
Classifier: License :: OSI Approved :: MIT License
Classifier: Operating System :: OS Independent
Requires-Python: >=3.8
Requires-Dist: numpy (>=1.20.0)
Requires-Dist: pandas (~=1.4.4)
Requires-Dist: paramiko (>=2.7.2)
Requires-Dist: psutil (>=5.7.2)
Requires-Dist: sortedcontainers (>=2.3.0)
Requires-Dist: pycryptodome (>=3.9.9)
Requires-Dist: plotly (>=4.14.1)
Requires-Dist: matplotlib (>=3.3.3)
Requires-Dist: scipy (>=1.6.0)
Requires-Dist: cryptography (>=3.3.1)
Requires-Dist: joblib (>=1.0.1)
Requires-Dist: scikit-learn (>=1.1)
Requires-Dist: lightgbm (>=3.2.1)
Requires-Dist: python-dateutil (>=2.8.2)
Requires-Dist: six (>=1.16.0)
Requires-Dist: seaborn (>=0.11.2)
Requires-Dist: xgboost (>=1.6.1)
Requires-Dist: scikit-optimize (>=0.9.0)
Requires-Dist: statsmodels (>=0.13.2)
Requires-Dist: tensorflow (>=2.10)
Requires-Dist: defusedxml (>=0.6.0)
Requires-Dist: transformers (>=4.26.0)
Requires-Dist: datasets (>=2.6.1)
Requires-Dist: keras (>=2.10.0)
Requires-Dist: ultralytics (>=8.0.59)
